{
  "run_id": "d7217f26924d",
  "overall": {
    "expectancy_R": 0.1968,
    "winrate": 0.5613207547169812,
    "profit_factor": 1.5054,
    "max_dd_usdt": 22.55,
    "trades_total": 212,
    "wins": 119,
    "losses": 93,
    "avg_win_R": 1.2931,
    "avg_loss_R": -1.2061
  },
  "by_setup": {
    "V3_TREND_BREAKOUT": {
      "expectancy_R": 0.1968,
      "winrate": 0.5613,
      "profit_factor": 1.5054,
      "trades_total": 212,
      "wins": 119,
      "losses": 93,
      "avg_win_R": 1.2931,
      "avg_loss_R": -1.2061,
      "max_dd_usdt": 22.55
    }
  },
  "exit_reason_counts": {
    "SL": 93,
    "TP": 119
  },
  "skip_reasons": {
    "bias_none": 672,
    "atr_filter_fail": 0,
    "range_too_small": 0,
    "breakout_not_triggered": 0,
    "retest_not_filled": 0,
    "bos_not_confirmed": 0,
    "ema20_confirm_fail": 0,
    "ema200_align_fail": 0,
    "ema20_ema50_fail": 0,
    "trend_weak": 0,
    "momo_confirm_fail": 0,
    "pullback_not_triggered": 0,
    "no_active_setup": 0,
    "score_below_min": 0,
    "max_abs_dist_4h": 0,
    "max_abs_dist_4h_hard": 0,
    "rate_limited": 0,
    "v3_bias_none": 0,
    "v3_trend_align_fail": 2832,
    "v3_sep_fail": 56,
    "v3_donchian_not_broken": 4857,
    "v3_body_too_small": 11,
    "v3_missing_5m": 0,
    "v3_5m_confirm_fail": 0,
    "v3_not_enough_15m_bars": 0,
    "v3_missing_4h_slope_inputs": 0,
    "v3_missing_1h_inputs": 0
  },
  "risk_invalid_count": 0
}